tests/__init__.py
tests/test_context.py
tests/test_nodes.py
tests/test_optimizer.py
tests/test_parser.py
tests/test_tokenizer.py
txtgen/__init__.py
txtgen/constants.py
txtgen/context.py
txtgen/interpreter.py
txtgen/nodes.py
txtgen/optimizer.py
txtgen/parser.py
txtgen/tokenizer.py
txtgen-1.0.0.dist-info/METADATA
txtgen-1.0.0.dist-info/WHEEL
txtgen-1.0.0.dist-info/top_level.txt
txtgen-1.0.0.dist-info/RECORD
