Metadata-Version: 2.1
Name: txtgen
Version: 1.0.0
Summary: Blazing-fast text generation DSL.
Home-page: https://github.com/dalloriam/txtgen
Author: dalloriam
Author-email: dalloriam@gmail.com
License: MIT
Platform: UNKNOWN
